nebulousai/__init__.py
nebulousai/agent.py
nebulousai/all_tools.py
nebulousai/prompts.py
nebulousai/tool_search.py
nebulousai/vectordb.py
nebulousai/core/__init__.py
nebulousai/core/brain.py
nebulousai/core/memory.py
nebulousai/core/planning.py
nebulousai/core/tool.py
nebulousai/feedback_loop/__init__.py
nebulousai/feedback_loop/human_feedback.py
nebulousai/feedback_loop/human_intervention.py
nebulousai/feedback_loop/learnings.py
nebulousai/utils/__init__.py
nebulousai/utils/llm.py
nebulousai-0.1.1.dist-info/LICENSE
nebulousai-0.1.1.dist-info/METADATA
nebulousai-0.1.1.dist-info/WHEEL
nebulousai-0.1.1.dist-info/top_level.txt
nebulousai-0.1.1.dist-info/RECORD
