Metadata-Version: 2.1
Name: nebulousai
Version: 0.1.1
License-File: LICENSE
Requires-Dist: litellm (==1.34.0)
Requires-Dist: wikipedia (==1.4.0)
Requires-Dist: duckduckgo-search (==6.1.0)
